python_watcher_metering-0.21.6.data/data/etc/watcher-metering/publisher.conf.sample
python_watcher_metering-0.21.6.data/data/etc/watcher-metering/agent.conf.sample
python_watcher_metering-0.21.6.dist-info/entry_points.txt
python_watcher_metering-0.21.6.dist-info/DESCRIPTION.rst
python_watcher_metering-0.21.6.dist-info/top_level.txt
python_watcher_metering-0.21.6.dist-info/RECORD
python_watcher_metering-0.21.6.dist-info/METADATA
python_watcher_metering-0.21.6.dist-info/pbr.json
python_watcher_metering-0.21.6.dist-info/metadata.json
python_watcher_metering-0.21.6.dist-info/WHEEL
watcher_metering/__init__.py
watcher_metering/doc.py
watcher_metering/version.py
watcher_metering/publisher/worker.py
watcher_metering/publisher/publisher.py
watcher_metering/publisher/opts.py
watcher_metering/publisher/app.py
watcher_metering/publisher/__init__.py
watcher_metering/publisher/base.py
watcher_metering/load/loadable.py
watcher_metering/load/loader.py
watcher_metering/load/__init__.py
watcher_metering/agent/manager.py
watcher_metering/agent/opts.py
watcher_metering/agent/loader.py
watcher_metering/agent/puller.py
watcher_metering/agent/app.py
watcher_metering/agent/agent.py
watcher_metering/agent/measurement.py
watcher_metering/agent/__init__.py
watcher_metering/agent/utils/observable.py
watcher_metering/agent/utils/__init__.py
watcher_metering/tests/__init__.py
watcher_metering/tests/publisher/app_fixtures.py
watcher_metering/tests/publisher/test_publisher.py
watcher_metering/tests/publisher/test_worker.py
watcher_metering/tests/publisher/__init__.py
watcher_metering/tests/publisher/publisher_fixtures.py
watcher_metering/tests/publisher/test_app.py
watcher_metering/tests/agent/app_fixtures.py
watcher_metering/tests/agent/test_agent.py
watcher_metering/tests/agent/agent_fixtures.py
watcher_metering/tests/agent/test_puller.py
watcher_metering/tests/agent/__init__.py
watcher_metering/tests/agent/test_app.py
watcher_metering/tests/store/test_influxdb.py
watcher_metering/tests/store/test_riemann.py
watcher_metering/tests/store/test_ceilometer.py
watcher_metering/tests/store/__init__.py
watcher_metering/tests/loader/_fixtures.py
watcher_metering/tests/loader/importable_opts.py
watcher_metering/tests/loader/test_loader.py
watcher_metering/tests/loader/__init__.py
watcher_metering/store/ceilometer.py
watcher_metering/store/opts.py
